{
  "db_name": "PostgreSQL",
  "query": "SELECT mf.id, mf.reviewer_id, dev.display_name AS reviewer_name, dev.admin AS reviewer_admin, mf.type AS \"feedback_type: _\", mf.feedback, mf.decision\n            FROM mod_feedback mf\n\t\t\tINNER JOIN developers dev ON dev.id = mf.reviewer_id\n            WHERE mf.mod_version_id = $1",
  "describe": {
    "columns": [
      {
        "ordinal": 0,
        "name": "id",
        "type_info": "Int4"
      },
      {
        "ordinal": 1,
        "name": "reviewer_id",
        "type_info": "Int4"
      },
      {
        "ordinal": 2,
        "name": "reviewer_name",
        "type_info": "Text"
      },
      {
        "ordinal": 3,
        "name": "reviewer_admin",
        "type_info": "Bool"
      },
      {
        "ordinal": 4,
        "name": "feedback_type: _",
        "type_info": {
          "Custom": {
            "name": "feedback_type",
            "kind": {
              "Enum": [
                "Positive",
                "Negative",
                "Suggestion",
                "Note"
              ]
            }
          }
        }
      },
      {
        "ordinal": 5,
        "name": "feedback",
        "type_info": "Text"
      },
      {
        "ordinal": 6,
        "name": "decision",
        "type_info": "Bool"
      }
    ],
    "parameters": {
      "Left": [
        "Int4"
      ]
    },
    "nullable": [
      false,
      false,
      false,
      false,
      false,
      false,
      false
    ]
  },
  "hash": "9b7acc44bb2484b620efd73816879188954aaf9632a417f7ba9362e218fcc021"
}
